jsonfeed2social/__init__.py
jsonfeed2social/__main__.py
jsonfeed2social/command_manager.py
jsonfeed2social/config.py
jsonfeed2social/exception.py
jsonfeed2social/jsonfeed.py
jsonfeed2social/social/__init__.py
jsonfeed2social/social/manager.py
jsonfeed2social/social/mastodon.py
jsonfeed2social/social/twitter.py
jsonfeed2social/utility.py
jsonfeed2social-1.3.0.dist-info/entry_points.txt
jsonfeed2social-1.3.0.dist-info/WHEEL
jsonfeed2social-1.3.0.dist-info/METADATA
jsonfeed2social-1.3.0.dist-info/RECORD
