Metadata-Version: 2.1
Name: jsonfeed2social
Version: 1.3.0
Summary: Tweet and toot from your jsonfeeed
Home-page: https://github.com/fundor333/jsonfeed2social
License: MIT
Keywords: jsonfeed,twitter,mastodon,social
Author: Fundor333
Author-email: fundor333@fundor333.com
Requires-Python: >=3.7.2,<4.0.0
Classifier: Development Status :: 4 - Beta
Classifier: License :: OSI Approved :: MIT License
Classifier: Programming Language :: Python :: 3
Classifier: Programming Language :: Python :: 3.10
Classifier: Programming Language :: Python :: 3.8
Classifier: Programming Language :: Python :: 3.9
Requires-Dist: Jinja2 (>=3.1.2,<4.0.0)
Requires-Dist: click (>=8.1.3,<9.0.0)
Requires-Dist: configparser (>=5.2.0,<6.0.0)
Requires-Dist: requests (>=2.28.0,<3.0.0)
Requires-Dist: tweepy (>=4.10.0,<5.0.0)
Project-URL: Repository, https://github.com/fundor333/jsonfeed2social
